{
  "$schema": "https://developer.microsoft.com/json-schemas/fabric/item/report/definition/visualContainer/2.8.0/schema.json",
  "name": "23308cc515b82d5153ea",
  "position": {
    "x": 1060.2061855670104,
    "y": 14.845360824742269,
    "z": 12000,
    "height": 56.288659793814432,
    "width": 114.43298969072164,
    "tabOrder": 12000
  },
  "visual": {
    "visualType": "image",
    "objects": {
      "image": [
        {
          "properties": {
            "sourceFile": {
              "image": {
                "name": {
                  "expr": {
                    "Literal": {
                      "Value": "'National_Health_Service_(England)_logo.svg'"
                    }
                  }
                },
                "url": {
                  "expr": {
                    "ResourcePackageItem": {
                      "PackageName": "RegisteredResources",
                      "PackageType": 1,
                      "ItemName": "National_Health_Service_(Engla6689306413799098.svg"
                    }
                  }
                },
                "scaling": {
                  "expr": {
                    "Literal": {
                      "Value": "'Normal'"
                    }
                  }
                }
              }
            },
            "transparency": {
              "expr": {
                "Literal": {
                  "Value": "50D"
                }
              }
            }
          }
        }
      ]
    },
    "drillFilterOtherVisuals": true
  }
}